Decorators/__init__.py
Decorators/cache_decorator.py
Decorators/debug_decorator.py
Decorators/execution_counter_decorator.py
Decorators/retry_decorator.py
Decorators/timing_decorators.py
Decorators/version.py
Decorators/Test_Decorators/__init__.py
Decorators/Test_Decorators/test_cache_decorator.py
Decorators/Test_Decorators/test_debug_decorator.py
Decorators/Test_Decorators/test_execution_counter.py
Decorators/Test_Decorators/test_retry_decorator.py
Decorators/Test_Decorators/test_timing_decorators.py
python_decorators_utils-0.1.5.dist-info/LICENSE
python_decorators_utils-0.1.5.dist-info/METADATA
python_decorators_utils-0.1.5.dist-info/WHEEL
python_decorators_utils-0.1.5.dist-info/top_level.txt
python_decorators_utils-0.1.5.dist-info/RECORD
