Metadata-Version: 2.1
Name: python_decorators_utils
Version: 0.1.5
Summary: A collection of useful Python decorators including timing and caching
Author-email: Udit Anand <getuditanand@gmail.com>
Classifier: Programming Language :: Python :: 3
Classifier: License :: OSI Approved :: MIT License
Classifier: Operating System :: OS Independent
Requires-Python: >=3.11
License-File: LICENSE
Requires-Dist: pytest
Requires-Dist: flake8
Requires-Dist: black
